wildfire_environment/__init__.py
wildfire_environment/core/agent.py
wildfire_environment/core/constants.py
wildfire_environment/core/grid.py
wildfire_environment/core/object.py
wildfire_environment/core/world.py
wildfire_environment/envs/__init__.py
wildfire_environment/envs/wildfire.py
wildfire_environment/multigrid.py
wildfire_environment/policy/__init__.py
wildfire_environment/policy/base.py
wildfire_environment/typing.py
wildfire_environment/utils/__init__.py
wildfire_environment/utils/misc.py
wildfire_environment/utils/rendering.py
wildfire_environment/utils/window.py
wildfire_environment-0.2.1.dist-info/LICENSE
wildfire_environment-0.2.1.dist-info/METADATA
wildfire_environment-0.2.1.dist-info/WHEEL
wildfire_environment-0.2.1.dist-info/RECORD
