Metadata-Version: 2.1
Name: wildfire-environment
Version: 0.2.1
Summary: Gym-based multi-agent environment to simulate wildfire fighting
Author: Niket
Author-email: 40545971+npnike10@users.noreply.github.com
Requires-Python: >=3.8.0,<4.0.0
Classifier: Programming Language :: Python :: 3
Classifier: Programming Language :: Python :: 3.8
Classifier: Programming Language :: Python :: 3.9
Classifier: Programming Language :: Python :: 3.10
Classifier: Programming Language :: Python :: 3.11
Classifier: Programming Language :: Python :: 3.12
Requires-Dist: gym (==0.21)
Requires-Dist: matplotlib (==3.7)
Requires-Dist: numpy (==1.22)
Requires-Dist: pip (==21)
Requires-Dist: protobuf (==3.20.3)
Requires-Dist: setuptools (==65.5.0)
Requires-Dist: wheel (==0.38.0)
